vyas_group_scripts/__init__.py
vyas_group_scripts/gen_batch.py
vyas_group_scripts/run_batch.py
vyas_group_scripts/small_utils.py
vyas_group_scripts/templates/g16_batch_inputs.py
vyas_group_scripts/templates/orca_batch_inputs.py
vyas_group_scripts-1.1.0.dist-info/WHEEL
vyas_group_scripts-1.1.0.dist-info/entry_points.txt
vyas_group_scripts-1.1.0.dist-info/METADATA
vyas_group_scripts-1.1.0.dist-info/RECORD
