Metadata-Version: 2.3
Name: vyas-group-scripts
Version: 1.1.0
Summary: Add your description here
Author: Ben Payton
Author-email: Ben Payton <bennyp2494@gmail.com>
Requires-Dist: argparse>=1.4.0
Requires-Dist: rich>=14.2.0
Requires-Dist: tqdm>=4.67.1
Requires-Python: >=3.9
